ebukafy/__init__.py
ebukafy-0.0.2.dist-info/LICENSE
ebukafy-0.0.2.dist-info/METADATA
ebukafy-0.0.2.dist-info/WHEEL
ebukafy-0.0.2.dist-info/top_level.txt
ebukafy-0.0.2.dist-info/RECORD
