Metadata-Version: 2.1
Name: ebukafy
Version: 0.0.2
Summary: Turn a text file into an epub chapter
Home-page: https://github.com/maticstric/ebukafy
Author: maticstric
Author-email: maticjecar@gmail.com
License: UNKNOWN
Platform: UNKNOWN
Classifier: Programming Language :: Python :: 3
Classifier: License :: OSI Approved :: MIT License
Classifier: Operating System :: OS Independent
Requires-Python: >=3.6
